maskrcnn/__init__.py
maskrcnn/dataset.py
maskrcnn/logger.py
maskrcnn/model.py
maskrcnn/test.py
maskrcnn/train.py
mask_rcnn_documents-1.0.post20230911134841.dist-info/METADATA
mask_rcnn_documents-1.0.post20230911134841.dist-info/WHEEL
mask_rcnn_documents-1.0.post20230911134841.dist-info/entry_points.txt
mask_rcnn_documents-1.0.post20230911134841.dist-info/top_level.txt
mask_rcnn_documents-1.0.post20230911134841.dist-info/RECORD
