Metadata-Version: 2.1
Name: mask-rcnn-documents
Version: 1.0.post20230911134841
Home-page: https://gitlab.univ-lr.fr/acadiie/document_layout_analysis/mask-rcnn
Author: Guillaume Bernard
Author-email: contact@guillaume-bernard.fr
Project-URL: Bug Tracker, https://gitlab.univ-lr.fr/acadiie/document_layout_analysis/mask-rcnn/-/issues
Classifier: Programming Language :: Python :: 3.10
Classifier: Topic :: Scientific/Engineering :: Artificial Intelligence
Classifier: Intended Audience :: Science/Research
Classifier: Topic :: Scientific/Engineering :: Information Analysis
Classifier: Operating System :: POSIX :: Linux
Classifier: Intended Audience :: Science/Research
Requires-Dist: numpy (>=1.23.5)
Requires-Dist: opencv-python (>=4.7)
Requires-Dist: Pillow (~=9.4)
Requires-Dist: pytorch-lightning (~=1.9)
Requires-Dist: torch (~=1.13)
Requires-Dist: torchvision (~=0.14)
